repo_stargazer/__about__.py
repo_stargazer/__init__.py
repo_stargazer/__main__.py
repo_stargazer/_app.py
repo_stargazer/_config.py
repo_stargazer/_embedder.py
repo_stargazer/_locations.py
repo_stargazer/_otel.py
repo_stargazer/_types.py
repo_stargazer/agent/__init__.py
repo_stargazer/agent/_agent.py
repo_stargazer/agent/_config.py
repo_stargazer/agent/_prompts.py
repo_stargazer/mcp_support/__init__.py
repo_stargazer/mcp_support/_server.py
repo_stargazer/ui/rsg/__init__.py
repo_stargazer/ui/rsg/agent.py
repo_stargazer-0.3.0.dist-info/METADATA
repo_stargazer-0.3.0.dist-info/WHEEL
repo_stargazer-0.3.0.dist-info/entry_points.txt
repo_stargazer-0.3.0.dist-info/licenses/LICENSE
repo_stargazer-0.3.0.dist-info/RECORD
