Metadata-Version: 2.4
Name: repo-stargazer
Version: 0.3.0
Summary: Tell me about my stars
Project-URL: repository, https://github.com/ksachdeva/repo-stargazer
Author: Sachdeva, Kapil
License-File: LICENSE
Classifier: Intended Audience :: Developers
Classifier: License :: OSI Approved :: Apache Software License
Classifier: Operating System :: OS Independent
Classifier: Programming Language :: Python
Classifier: Programming Language :: Python :: 3
Classifier: Programming Language :: Python :: 3.11
Classifier: Programming Language :: Python :: 3.12
Classifier: Programming Language :: Python :: 3.13
Classifier: Topic :: Software Development :: Libraries :: Python Modules
Requires-Python: >=3.11
Requires-Dist: arize-phoenix-otel>=0.12.1
Requires-Dist: fastparquet>=2024.11.0
Requires-Dist: google-adk>=1.5.0
Requires-Dist: httpx>=0.28.1
Requires-Dist: lancedb>=0.23.0
Requires-Dist: langchain-community>=0.3.24
Requires-Dist: langchain-core>=0.3.64
Requires-Dist: langchain-ollama>=0.3.3
Requires-Dist: langchain-openai>=0.3.21
Requires-Dist: langchain-text-splitters>=0.3.8
Requires-Dist: langchain>=0.3.25
Requires-Dist: litellm>=1.73.0
Requires-Dist: mcp>=1.9.3
Requires-Dist: mpire>=2.10.2
Requires-Dist: openinference-instrumentation-google-adk>=0.1.1
Requires-Dist: pandas>=2.3.0
Requires-Dist: pydantic-settings>=2.9.1
Requires-Dist: pydantic>=2.11.5
Requires-Dist: pygithub>=2.6.1
Requires-Dist: rich>=14.0.0
Requires-Dist: typer>=0.16.0
Requires-Dist: xdg-base-dirs>=6.0.2
